grepbible/__init__.py
grepbible/bible_manager.py
grepbible/cli.py
grepbible/fuzz/fuzz_search.py
grepbible/rag/__init__.py
grepbible/rag/rag_indexer.py
grepbible/rag/rag_query.py
grepbible/static/__init__.py
grepbible/static/acronyms.txt
grepbible/static/ch2num.py
grepbible/static/full_names.txt
grepbible/utils.py
grepbible-0.3.7.dist-info/LICENSE.txt
grepbible-0.3.7.dist-info/METADATA
grepbible-0.3.7.dist-info/WHEEL
grepbible-0.3.7.dist-info/entry_points.txt
grepbible-0.3.7.dist-info/RECORD
