Metadata-Version: 2.1
Name: grepbible
Version: 0.3.7
Summary: 
License: MIT
Author: Maxim Litvak
Author-email: maxim@litvak.eu
Requires-Python: >=3.9,<4.0
Classifier: License :: OSI Approved :: MIT License
Classifier: Programming Language :: Python :: 3
Classifier: Programming Language :: Python :: 3.9
Classifier: Programming Language :: Python :: 3.10
Classifier: Programming Language :: Python :: 3.11
Provides-Extra: ml
Requires-Dist: faiss-cpu (>=1.7.4) ; extra == "ml"
Requires-Dist: importlib-resources (>=6.1.3,<7.0.0)
Requires-Dist: jsonschema (>=3.0) ; extra == "ml"
Requires-Dist: langchain (==0.2.1) ; extra == "ml"
Requires-Dist: langchain-core (<0.3) ; extra == "ml"
Requires-Dist: langdetect (>=1.0.9,<2.0.0) ; extra == "ml"
Requires-Dist: numpy (>=1.18.5,<1.26.0) ; extra == "ml"
Requires-Dist: peft (>=0.4.0) ; extra == "ml"
Requires-Dist: pydantic (>=1.6.2,<2.0.0) ; extra == "ml"
Requires-Dist: rapidfuzz (>=3.13.0,<4.0.0)
Requires-Dist: requests (>=2.31.0,<3.0.0)
Requires-Dist: scikit-learn (==1.6.1) ; extra == "ml"
Requires-Dist: scipy (>=1.9.0) ; extra == "ml"
Requires-Dist: sentence-transformers (>=2.2.2) ; extra == "ml"
Requires-Dist: srsly (>=2.4.0,<3.0.0) ; extra == "ml"
Requires-Dist: toolz ; extra == "ml"
Requires-Dist: torch (==2.1.0) ; extra == "ml"
